[{"keywords":["Japanese"],"derivedData":{"listStartDate":1020,"listEndDate":1300,"extendedName":"Later Heian and Kamakura Samurai  1020 to 1300 AD"},"sortId":338,"sublistId":"b","name":"Later Heian and Kamakura Samurai","invasionRatings":[{"_id":"6153508d03385c0016b825e3","value":0,"note":null}],"maneuverRatings":[{"_id":"6153508d03385c0016b825e4","value":1,"note":null}],"homeTopographies":[{"values":["Arable"," Hilly"],"_id":"6153508d03385c0016b825e5","note":""}],"listId":337,"dateRanges":[{"_id":"6153508d03385c0016b825e6","startDate":1020,"endDate":1300}],"troopOptions":[{"_id":"615351b603385c0016b88cea","min":3,"max":9,"dateRanges":[],"troopEntries":[{"_id":"615351b603385c0016b88ceb","troopTypeCode":"HBW","dismountTypeCode":null,"note":null}],"description":"Mounted bushi","note":"","core":"","battleCardEntries":[]},{"_id":"615351b603385c0016b88cec","min":0,"max":9,"dateRanges":[],"troopEntries":[{"_id":"615351b603385c0016b88ced","troopTypeCode":"RBL","dismountTypeCode":null,"note":null}],"description":"Footmen armed with naginata","note":"","core":"","battleCardEntries":[]},{"_id":"615351b603385c0016b88cee","min":0,"max":3,"dateRanges":[],"troopEntries":[{"_id":"615351b603385c0016b88cef","troopTypeCode":"RDR","dismountTypeCode":null,"note":null}],"description":"Armored footmen armed with naginata","note":"","core":"all","battleCardEntries":[]},{"_id":"615351b603385c0016b88cf0","min":0,"max":3,"dateRanges":[],"troopEntries":[{"_id":"615351b603385c0016b88cf1","troopTypeCode":"ARC","dismountTypeCode":null,"note":null}],"description":"Armored bowmen","note":"","core":"all","battleCardEntries":[]},{"_id":"615351b603385c0016b88cf2","min":0,"max":2,"dateRanges":[],"troopEntries":[{"_id":"615351b603385c0016b88cf3","troopTypeCode":"RBL","dismountTypeCode":null,"note":null}],"description":"Inji 'ruffians'","note":"","core":"","battleCardEntries":[]}],"troopEntriesForGeneral":[{"_id":"615351b603385c0016b88cf4","troopEntries":[{"_id":"615351b603385c0016b88cf5","troopTypeCode":"HBW","dismountTypeCode":null,"note":null}]}],"allyOptions":[],"battleCardEntries":[{"_id":"615351b603385c0016b88cf6","min":null,"max":null,"battleCardCode":"FC","note":"Palisade"}],"showTroopOptionDescriptions":true,"status":"Revised","id":"5fb1b9f4e1af06001770a35d"},{"keywords":[],"derivedData":{"listStartDate":918,"listEndDate":1392,"extendedName":"Goryeo Korean  918 to 1392 AD"},"sortId":339,"sublistId":"a","name":"Goryeo Korean","invasionRatings":[{"_id":"6153508d03385c0016b825e9","value":1,"note":null}],"maneuverRatings":[{"_id":"6153508d03385c0016b825ea","value":3,"note":"With Guerrilla allies or 918-1170 AD"},{"_id":"6153508d03385c0016b825eb","value":2,"note":"1171-1392 AD with no Guerrillas"}],"homeTopographies":[{"values":["Hilly"],"_id":"6153508d03385c0016b825ec","note":""}],"listId":338,"dateRanges":[{"_id":"6153508d03385c0016b825ed","startDate":918,"endDate":1392}],"troopOptions":[{"_id":"615351b603385c0016b88cf7","min":1,"max":3,"dateRanges":[],"troopEntries":[{"_id":"615351b603385c0016b88cf8","troopTypeCode":"HBW","dismountTypeCode":null,"note":null},{"_id":"615351b603385c0016b88cf9","troopTypeCode":"JCV","dismountTypeCode":null,"note":null}],"description":"Kwanggun horsemen armed with bow or lance","note":"","core":"","battleCardEntries":[]},{"_id":"615351b603385c0016b88cfa","min":0,"max":2,"dateRanges":[],"troopEntries":[{"_id":"615351b603385c0016b88cfb","troopTypeCode":"BAD","dismountTypeCode":null,"note":null}],"description":"Militia horsemen","note":"","core":"","battleCardEntries":[]},{"_id":"615351b603385c0016b88cfc","min":1,"max":1,"dateRanges":[],"troopEntries":[{"_id":"615351b603385c0016b88cfd","troopTypeCode":"HBW","dismountTypeCode":null,"note":null}],"description":"Light horse archers","note":"","core":"","battleCardEntries":[]},{"_id":"615351b603385c0016b88cfe","min":1,"max":1,"dateRanges":[],"troopEntries":[{"_id":"615351b603385c0016b88cff","troopTypeCode":"ARC","dismountTypeCode":null,"note":null}],"description":"Kwanggun bowmen","note":"","core":"all","battleCardEntries":[]},{"_id":"615351b603385c0016b88d00","min":1,"max":1,"dateRanges":[],"troopEntries":[{"_id":"615351b603385c0016b88d01","troopTypeCode":"SPR","dismountTypeCode":null,"note":null}],"description":"Kwanggun spearmen","note":"","core":"all","battleCardEntries":[{"_id":"615351b603385c0016b88d02","min":null,"max":null,"battleCardCode":"HL","note":null}]},{"_id":"615351b603385c0016b88d03","min":2,"max":4,"dateRanges":[],"troopEntries":[{"_id":"615351b603385c0016b88d04","troopTypeCode":"BLV","dismountTypeCode":null,"note":null}],"description":"Militia bowmen","note":"","core":"all","battleCardEntries":[]},{"_id":"615351b603385c0016b88d05","min":2,"max":4,"dateRanges":[],"troopEntries":[{"_id":"615351b603385c0016b88d06","troopTypeCode":"HFT","dismountTypeCode":null,"note":null}],"description":"Militia spearmen","note":"","core":"all","battleCardEntries":[]},{"_id":"615351b603385c0016b88d07","min":0,"max":1,"dateRanges":[],"troopEntries":[{"_id":"615351b603385c0016b88d08","troopTypeCode":"WWG","dismountTypeCode":null,"note":null}],"description":"Battle wagons or carriages with swords on their axles","note":"","core":"","battleCardEntries":[]},{"_id":"615351b603385c0016b88d09","min":0,"max":1,"dateRanges":[],"troopEntries":[{"_id":"615351b603385c0016b88d0a","troopTypeCode":"ART","dismountTypeCode":null,"note":null}],"description":"Heavy stone-throwers","note":"","core":"","battleCardEntries":[]}],"troopEntriesForGeneral":[{"_id":"615351b603385c0016b88d0b","troopEntries":[{"_id":"615351b603385c0016b88d0c","troopTypeCode":"HBW","dismountTypeCode":null,"note":null},{"_id":"615351b603385c0016b88d0d","troopTypeCode":"JCV","dismountTypeCode":null,"note":null}]}],"allyOptions":[{"_id":"615351b603385c0016b88d0e","dateRange":{"_id":"615351b603385c0016b88d0f","startDate":926,"endDate":1107},"note":null,"allyEntries":[{"_id":"615351b603385c0016b88d10","name":"Jurchen auxiliaries","allyArmyList":"6153519c03385c0016b84c1b"}]},{"_id":"615351b603385c0016b88d11","dateRange":{"_id":"615351b603385c0016b88d12","startDate":1217,"endDate":1218},"note":null,"allyEntries":[{"_id":"615351b603385c0016b88d13","name":"Jurchen Jin allies","allyArmyList":"6153519c03385c0016b84b31"}]},{"_id":"615351b603385c0016b88d14","dateRange":{"_id":"615351b603385c0016b88d15","startDate":1231,"endDate":1273},"note":null,"allyEntries":[{"_id":"615351b603385c0016b88d16","name":"(Anti-Mongol Rebellions) Guerrillas","allyArmyList":"6153519c03385c0016b84c22"}]},{"_id":"615351b603385c0016b88d17","dateRange":{"_id":"615351b603385c0016b88d18","startDate":1273,"endDate":1392},"note":null,"allyEntries":[{"_id":"615351b603385c0016b88d19","name":"Mongol allies","allyArmyList":"6153519c03385c0016b84b49"}]}],"battleCardEntries":[],"showTroopOptionDescriptions":true,"status":"Revised","id":"5fb1b9f4e1af06001770a363"},{"keywords":[],"derivedData":{"listStartDate":960,"listEndDate":1126,"extendedName":"Northern Song Chinese  960 to 1126 AD"},"sortId":327,"sublistId":"a","name":"Northern Song Chinese","invasionRatings":[{"_id":"6153508d03385c0016b82544","value":3,"note":null}],"maneuverRatings":[{"_id":"6153508d03385c0016b82545","value":3,"note":"Under Zhao Kuangyin 960-976 AD"},{"_id":"6153508d03385c0016b82546","value":2,"note":"Otherwise"}],"homeTopographies":[{"values":["Forest"," Arable"," Hilly"],"_id":"6153508d03385c0016b82547","note":""}],"listId":326,"dateRanges":[{"_id":"6153508d03385c0016b82548","startDate":960,"endDate":1126}],"troopOptions":[{"_id":"615351b403385c0016b88a7b","min":1,"max":2,"dateRanges":[],"troopEntries":[{"_id":"615351b403385c0016b88a7c","troopTypeCode":"ECV","dismountTypeCode":null,"note":null}],"description":"Elite horsemen","note":"","core":"","battleCardEntries":[]},{"_id":"615351b403385c0016b88a7d","min":0,"max":1,"dateRanges":[{"_id":"615351b403385c0016b88a7e","startDate":960,"endDate":978}],"troopEntries":[{"_id":"615351b403385c0016b88a7f","troopTypeCode":"HBW","dismountTypeCode":null,"note":null}],"description":"Chinese horse archers","note":"","core":"","battleCardEntries":[]},{"_id":"615351b403385c0016b88a80","min":0,"max":1,"dateRanges":[{"_id":"615351b403385c0016b88a81","startDate":979,"endDate":1054}],"troopEntries":[{"_id":"615351b403385c0016b88a82","troopTypeCode":"BAD","dismountTypeCode":null,"note":null}],"description":"Chinese horsemen","note":"","core":"","battleCardEntries":[]},{"_id":"615351b403385c0016b88a83","min":4,"max":8,"dateRanges":[],"troopEntries":[{"_id":"615351b403385c0016b88a84","troopTypeCode":"PAV","dismountTypeCode":null,"note":null}],"description":"Imperial infantry","note":"","core":"all","battleCardEntries":[{"_id":"615351b403385c0016b88a85","min":null,"max":null,"battleCardCode":"HL","note":null}]},{"_id":"615351b403385c0016b88a86","min":0,"max":2,"dateRanges":[],"troopEntries":[{"_id":"615351b403385c0016b88a87","troopTypeCode":"RBL","dismountTypeCode":null,"note":null}],"description":"Provincial infantry armed with mixed weapons","note":"","core":"","battleCardEntries":[]},{"_id":"615351b403385c0016b88a88","min":0,"max":3,"dateRanges":[],"troopEntries":[{"_id":"615351b403385c0016b88a89","troopTypeCode":"BLV","dismountTypeCode":null,"note":null}],"description":"Provincial crossbowmen and bowmen","note":"","core":"","battleCardEntries":[]},{"_id":"615351b403385c0016b88a8a","min":0,"max":1,"dateRanges":[],"troopEntries":[{"_id":"615351b403385c0016b88a8b","troopTypeCode":"EFT","dismountTypeCode":null,"note":null},{"_id":"615351b403385c0016b88a8c","troopTypeCode":"RDR","dismountTypeCode":null,"note":null}],"description":"Picked infantry armed with axe or long swords, or with sword and shield","note":"","core":"","battleCardEntries":[]},{"_id":"615351b403385c0016b88a8d","min":0,"max":1,"dateRanges":[{"_id":"615351b403385c0016b88a8e","startDate":1090,"endDate":1126}],"troopEntries":[{"_id":"615351b403385c0016b88a8f","troopTypeCode":"ARC","dismountTypeCode":null,"note":null}],"description":"Companies of bowmen","note":"","core":"all","battleCardEntries":[{"_id":"615351b403385c0016b88a90","min":null,"max":null,"battleCardCode":"MI","note":null}]},{"_id":"615351b403385c0016b88a91","min":0,"max":3,"dateRanges":[],"troopEntries":[{"_id":"615351b403385c0016b88a92","troopTypeCode":"HRD","dismountTypeCode":null,"note":null}],"description":"Militia","note":"","core":"all","battleCardEntries":[]},{"_id":"615351b403385c0016b88a93","min":0,"max":1,"dateRanges":[{"_id":"615351b403385c0016b88a94","startDate":1070,"endDate":1086}],"troopEntries":[{"_id":"615351b403385c0016b88a95","troopTypeCode":"HFT","dismountTypeCode":null,"note":null}],"description":"Retrained militia spear","note":"","core":"all","battleCardEntries":[]},{"_id":"615351b403385c0016b88a96","min":0,"max":2,"dateRanges":[{"_id":"615351b403385c0016b88a97","startDate":1070,"endDate":1086}],"troopEntries":[{"_id":"615351b403385c0016b88a98","troopTypeCode":"BLV","dismountTypeCode":null,"note":null}],"description":"Retrained militia crossbowmen","note":"","core":"all","battleCardEntries":[]},{"_id":"615351b403385c0016b88a99","min":0,"max":2,"dateRanges":[{"_id":"615351b403385c0016b88a9a","startDate":1055,"endDate":1126}],"troopEntries":[{"_id":"615351b403385c0016b88a9b","troopTypeCode":"WWG","dismountTypeCode":null,"note":null}],"description":"War wagons","note":"","core":"all","battleCardEntries":[]},{"_id":"615351b403385c0016b88a9c","min":0,"max":1,"dateRanges":[],"troopEntries":[{"_id":"615351b403385c0016b88a9d","troopTypeCode":"ART","dismountTypeCode":null,"note":null}],"description":"Heavy stone-throwers or bolt-shooting giant crossbows","note":"","core":"all","battleCardEntries":[]}],"troopEntriesForGeneral":[{"_id":"615351b403385c0016b88a9e","troopEntries":[{"_id":"615351b403385c0016b88a9f","troopTypeCode":"ECV","dismountTypeCode":null,"note":null}]}],"allyOptions":[{"_id":"615351b403385c0016b88aa0","dateRange":{"_id":"615351b403385c0016b88aa1","startDate":974,"endDate":976},"note":null,"allyEntries":[{"_id":"615351b403385c0016b88aa2","name":"Wu-Yueh allies","allyArmyList":"6153519b03385c0016b84a73"}]},{"_id":"615351b403385c0016b88aa3","dateRange":{"_id":"615351b403385c0016b88aa4","startDate":960,"endDate":978},"note":null,"allyEntries":[{"_id":"615351b403385c0016b88aa5","name":"Hsi allies","allyArmyList":"6153519b03385c0016b84a1f"}]},{"_id":"615351b403385c0016b88aa6","dateRange":{"_id":"615351b403385c0016b88aa7","startDate":979,"endDate":1054},"note":null,"allyEntries":[{"_id":"615351b403385c0016b88aa8","name":"(in South China) Zhuang tribal infantry","allyArmyList":"6153519b03385c0016b84b22"}]}],"battleCardEntries":[{"_id":"615351b403385c0016b88aa9","battleCardCode":"PD","note":"Ditch and bank, or palisade","min":0,"max":3},{"_id":"615351b403385c0016b88aaa","battleCardCode":"SC","note":"Stampeding oxen with burning brands"}],"showTroopOptionDescriptions":true,"status":"Revised","id":"5fb1b9f3e1af06001770a2be"},{"keywords":["Chinese"],"derivedData":{"listStartDate":1127,"listEndDate":1279,"extendedName":"Southern Song Chinese  1127 to 1279 AD"},"sortId":327,"sublistId":"d","name":"Southern Song Chinese","invasionRatings":[{"_id":"6153508d03385c0016b8254d","value":0,"note":null}],"maneuverRatings":[{"_id":"6153508d03385c0016b8254e","value":2,"note":null}],"homeTopographies":[{"values":["Forest"," Arable"," Hilly"],"_id":"6153508d03385c0016b8254f","note":""}],"listId":326,"dateRanges":[{"_id":"6153508d03385c0016b82550","startDate":1127,"endDate":1279}],"troopOptions":[{"_id":"615351b503385c0016b88aab","min":0,"max":1,"dateRanges":[],"troopEntries":[{"_id":"615351b503385c0016b88aac","troopTypeCode":"BAD","dismountTypeCode":null,"note":null}],"description":"Chinese horsemen","note":"","core":"","battleCardEntries":[]},{"_id":"615351b503385c0016b88aad","min":0,"max":2,"dateRanges":[{"_id":"615351b503385c0016b88aae","startDate":1250,"endDate":1279}],"troopEntries":[{"_id":"615351b503385c0016b88aaf","troopTypeCode":"HBW","dismountTypeCode":null,"note":null}],"description":"Mongol horse archers","note":"","core":"","battleCardEntries":[]},{"_id":"615351b503385c0016b88ab0","min":5,"max":10,"dateRanges":[],"troopEntries":[{"_id":"615351b503385c0016b88ab1","troopTypeCode":"PAV","dismountTypeCode":null,"note":null}],"description":"Imperial infantry","note":"","core":"all","battleCardEntries":[{"_id":"615351b503385c0016b88ab2","min":null,"max":null,"battleCardCode":"HL","note":null}]},{"_id":"615351b503385c0016b88ab3","min":0,"max":2,"dateRanges":[],"troopEntries":[{"_id":"615351b503385c0016b88ab4","troopTypeCode":"RBL","dismountTypeCode":null,"note":null}],"description":"Provincial infantry armed with mixed weapons","note":"","core":"","battleCardEntries":[]},{"_id":"615351b503385c0016b88ab5","min":0,"max":3,"dateRanges":[],"troopEntries":[{"_id":"615351b503385c0016b88ab6","troopTypeCode":"BLV","dismountTypeCode":null,"note":null}],"description":"Provincial crossbowmen and bowmen","note":"","core":"","battleCardEntries":[]},{"_id":"615351b503385c0016b88ab7","min":0,"max":1,"dateRanges":[],"troopEntries":[{"_id":"615351b503385c0016b88ab8","troopTypeCode":"EFT","dismountTypeCode":null,"note":null},{"_id":"615351b503385c0016b88ab9","troopTypeCode":"RDR","dismountTypeCode":null,"note":null}],"description":"Picked infantry armed with axe or long swords, or with sword and shield","note":"","core":"","battleCardEntries":[]},{"_id":"615351b503385c0016b88aba","min":0,"max":3,"dateRanges":[],"troopEntries":[{"_id":"615351b503385c0016b88abb","troopTypeCode":"HRD","dismountTypeCode":null,"note":null}],"description":"Militia","note":"","core":"","battleCardEntries":[]},{"_id":"615351b503385c0016b88abc","min":0,"max":1,"dateRanges":[],"troopEntries":[{"_id":"615351b503385c0016b88abd","troopTypeCode":"SKM","dismountTypeCode":null,"note":null}],"description":"Fire-lance foot","note":"","core":"","battleCardEntries":[]},{"_id":"615351b503385c0016b88abe","min":0,"max":2,"dateRanges":[],"troopEntries":[{"_id":"615351b503385c0016b88abf","troopTypeCode":"WWG","dismountTypeCode":null,"note":null}],"description":"War wagons","note":"","core":"all","battleCardEntries":[]},{"_id":"615351b503385c0016b88ac0","min":1,"max":2,"dateRanges":[],"troopEntries":[{"_id":"615351b503385c0016b88ac1","troopTypeCode":"ART","dismountTypeCode":null,"note":null}],"description":"Heavy stone-throwers or bolt-shooting giant crossbows","note":"","core":"all","battleCardEntries":[]}],"troopEntriesForGeneral":[{"_id":"615351b503385c0016b88ac2","troopEntries":[{"_id":"615351b503385c0016b88ac3","troopTypeCode":"BAD","dismountTypeCode":null,"note":null}]},{"_id":"615351b503385c0016b88ac4","troopEntries":[{"_id":"615351b503385c0016b88ac5","troopTypeCode":"PAV","dismountTypeCode":null,"note":null},{"_id":"615351b503385c0016b88ac6","troopTypeCode":"EFT","dismountTypeCode":null,"note":null},{"_id":"615351b503385c0016b88ac7","troopTypeCode":"RDR","dismountTypeCode":null,"note":null}]}],"allyOptions":[{"_id":"615351b503385c0016b88ac8","dateRange":null,"note":null,"allyEntries":[{"_id":"615351b503385c0016b88ac9","name":"Zhuang tribal infantry","allyArmyList":"6153519b03385c0016b84b22"}]},{"_id":"615351b503385c0016b88aca","dateRange":{"_id":"615351b503385c0016b88acb","startDate":1250,"endDate":1279},"note":null,"allyEntries":[{"_id":"615351b503385c0016b88acc","name":"She Army","allyArmyList":"6153519b03385c0016b84b21"}]}],"battleCardEntries":[{"_id":"615351b503385c0016b88acd","battleCardCode":"SC","note":"Stampeding oxen with burning brands"}],"showTroopOptionDescriptions":true,"status":"Revised","id":"5fb1b9f3e1af06001770a2c7"},{"keywords":["Mongol","Chinese"],"derivedData":{"listStartDate":1276,"listEndDate":1368,"extendedName":"Yuan in Japan and S.E. Asia  1276 to 1368 AD"},"sortId":329,"sublistId":"f","name":"Yuan in Japan and S.E. Asia","invasionRatings":[{"_id":"6153508d03385c0016b8257a","value":2,"note":null}],"maneuverRatings":[{"_id":"6153508d03385c0016b8257b","value":2,"note":null}],"homeTopographies":[{"values":["Arable"," Hilly"," Forest"],"_id":"6153508d03385c0016b8257c","note":""}],"listId":328,"dateRanges":[{"_id":"6153508d03385c0016b8257d","startDate":1276,"endDate":1368}],"troopOptions":[{"_id":"615351b503385c0016b88b83","min":1,"max":2,"dateRanges":[],"troopEntries":[{"_id":"615351b503385c0016b88b84","troopTypeCode":"ECV","dismountTypeCode":null,"note":null}],"description":"Guard horsemen","note":"","core":"all","battleCardEntries":[{"_id":"615351b503385c0016b88b85","min":null,"max":null,"battleCardCode":"DD","note":"as Archer"}]},{"_id":"615351b503385c0016b88b86","min":0,"max":1,"dateRanges":[],"troopEntries":[{"_id":"615351b503385c0016b88b87","troopTypeCode":"EFT","dismountTypeCode":null,"note":null}],"description":"Chinese guards","note":"","core":"all","battleCardEntries":[]},{"_id":"615351b503385c0016b88b88","min":2,"max":4,"dateRanges":[{"_id":"615351b503385c0016b88b89","startDate":1276,"endDate":1300}],"troopEntries":[{"_id":"615351b503385c0016b88b8a","troopTypeCode":"HBW","dismountTypeCode":null,"note":null}],"description":"Menggu jun (Mongol army) horse archers","note":"","core":"","battleCardEntries":[{"_id":"615351b503385c0016b88b8b","min":null,"max":null,"battleCardCode":"DD","note":"as Archer"}]},{"_id":"615351b503385c0016b88b8c","min":2,"max":2,"dateRanges":[{"_id":"615351b503385c0016b88b8d","startDate":1301,"endDate":1368}],"troopEntries":[{"_id":"615351b503385c0016b88b8e","troopTypeCode":"BAD","dismountTypeCode":null,"note":null}],"description":"Menggu jun (Mongol army) settled Mongol horse archers with inferior mounts and training","note":"","core":"","battleCardEntries":[{"_id":"615351b503385c0016b88b8f","min":null,"max":null,"battleCardCode":"DD","note":"as Archer"}]},{"_id":"615351b503385c0016b88b90","min":0,"max":2,"dateRanges":[{"_id":"615351b503385c0016b88b91","startDate":1301,"endDate":1368}],"troopEntries":[{"_id":"615351b503385c0016b88b92","troopTypeCode":"HBW","dismountTypeCode":null,"note":null},{"_id":"615351b503385c0016b88b93","troopTypeCode":"BAD","dismountTypeCode":null,"note":null}],"description":"Mongol horse archers who retained their steppe skills; or Menggu jun settled Mongol horse archers with inferior mounts and training","note":"","core":"","battleCardEntries":[{"_id":"615351b503385c0016b88b94","min":null,"max":null,"battleCardCode":"DD","note":"as Archer"}]},{"_id":"615351b503385c0016b88b95","min":0,"max":3,"dateRanges":[],"troopEntries":[{"_id":"615351b503385c0016b88b96","troopTypeCode":"PAV","dismountTypeCode":null,"note":null}],"description":"South Chinese halberdiers and crossbowmen in mixed formations","note":"","core":"all","battleCardEntries":[]},{"_id":"615351b503385c0016b88b97","min":0,"max":2,"dateRanges":[],"troopEntries":[{"_id":"615351b503385c0016b88b98","troopTypeCode":"HFT","dismountTypeCode":null,"note":null}],"description":"South Chinese halberdiers","note":"","core":"all","battleCardEntries":[]},{"_id":"615351b503385c0016b88b99","min":0,"max":2,"dateRanges":[],"troopEntries":[{"_id":"615351b503385c0016b88b9a","troopTypeCode":"BLV","dismountTypeCode":null,"note":null}],"description":"South Chinese crossbowmen","note":"","core":"all","battleCardEntries":[]},{"_id":"615351b503385c0016b88b9b","min":0,"max":1,"dateRanges":[],"troopEntries":[{"_id":"615351b503385c0016b88b9c","troopTypeCode":"ART","dismountTypeCode":null,"note":null}],"description":"Bolt shooters and counterweight stone-throwers","note":"","core":"all","battleCardEntries":[]}],"troopEntriesForGeneral":[{"_id":"615351b503385c0016b88b9d","troopEntries":[{"_id":"615351b503385c0016b88b9e","troopTypeCode":"ECV","dismountTypeCode":null,"note":null},{"_id":"615351b503385c0016b88b9f","troopTypeCode":"HBW","dismountTypeCode":null,"note":null}]}],"allyOptions":[{"_id":"615351b503385c0016b88ba0","dateRange":null,"note":null,"allyEntries":[{"_id":"615351b503385c0016b88ba1","name":"North Chinese subjects","allyArmyList":"6153519c03385c0016b84b7d"}]},{"_id":"615351b503385c0016b88ba2","dateRange":null,"note":null,"allyEntries":[{"_id":"615351b503385c0016b88ba3","name":"(only in Java) Javanese allies","allyArmyList":"6153519a03385c0016b848ca"}]},{"_id":"615351b503385c0016b88ba4","dateRange":null,"note":null,"allyEntries":[{"_id":"615351b503385c0016b88ba5","name":"(only in Korea) Korean allies","allyArmyList":"6153519c03385c0016b84c12"}]}],"battleCardEntries":[],"showTroopOptionDescriptions":true,"status":"Revised","id":"5fb1b9f3e1af06001770a2f4"}]